{"teamCode":"ESP","teamName":"Spain","players":{"ESP::RAYA David":{"teamCode":"ESP","teamName":"Spain","playerName":"RAYA David","commonName":"David Raya Martín","originalName":"David RAYA MARTÍN","nameOnShirt":"RAYA","aliases":["David Raya Martín","Raya Martín David","David Raya","Raya","RAYA David"],"zhName":"戴维·拉亚","displayName":"戴维·拉亚（David Raya Martín）"},"ESP::PUBILL Marc":{"teamCode":"ESP","teamName":"Spain","playerName":"PUBILL Marc","commonName":"Marc Pubill Pages","originalName":"Marc PUBILL PAGES","nameOnShirt":"MARC PUBILL","aliases":["Marc Pubill Pages","Pubill Pages Marc","Marc Marc Pubill","Marc Pubill","PUBILL Marc"],"zhName":"馬克·普比爾","displayName":"馬克·普比爾（Marc Pubill Pages）"},"ESP::GRIMALDO Alex":{"teamCode":"ESP","teamName":"Spain","playerName":"GRIMALDO Alex","commonName":"Alejandro Grimaldo García","originalName":"Alejandro GRIMALDO GARCÍA","nameOnShirt":"GRIMALDO","aliases":["Alejandro Grimaldo García","Grimaldo García Alejandro","Alejandro Grimaldo","Grimaldo","Alex Grimaldo","GRIMALDO Alex"],"displayName":"Alejandro Grimaldo García"},"ESP::GARCIA Eric":{"teamCode":"ESP","teamName":"Spain","playerName":"GARCIA Eric","commonName":"Eric García Martret","originalName":"Eric GARCÍA MARTRET","nameOnShirt":"ERIC","aliases":["Eric García Martret","García Martret Eric","Eric Eric","Eric","Eric Garcia","GARCIA Eric"],"displayName":"Eric García Martret"},"ESP::LLORENTE Marcos":{"teamCode":"ESP","teamName":"Spain","playerName":"LLORENTE Marcos","commonName":"Marcos Llorente Moreno","originalName":"Marcos LLORENTE MORENO","nameOnShirt":"M. LLORENTE","aliases":["Marcos Llorente Moreno","Llorente Moreno Marcos","Marcos M Llorente","M Llorente","Marcos Llorente","LLORENTE Marcos"],"zhName":"馬科斯·略倫特","displayName":"馬科斯·略倫特（Marcos Llorente Moreno）"},"ESP::MERINO Mikel":{"teamCode":"ESP","teamName":"Spain","playerName":"MERINO Mikel","commonName":"Mikel Merino Zazón","originalName":"Mikel MERINO ZAZÓN","nameOnShirt":"MERINO","aliases":["Mikel Merino Zazón","Merino Zazón Mikel","Mikel Merino","Merino","MERINO Mikel"],"zhName":"米克尔·梅里诺","displayName":"米克尔·梅里诺（Mikel Merino Zazón）"},"ESP::TORRES Ferran":{"teamCode":"ESP","teamName":"Spain","playerName":"TORRES Ferran","commonName":"Ferran Torres García","originalName":"Ferran TORRES GARCÍA","nameOnShirt":"FERRAN","aliases":["Ferran Torres García","Torres García Ferran","Ferran Ferran","Ferran","Ferran Torres","TORRES Ferran"],"zhName":"费兰·托雷斯","displayName":"费兰·托雷斯（Ferran Torres García）"},"ESP::RUIZ Fabian":{"teamCode":"ESP","teamName":"Spain","playerName":"RUIZ Fabian","commonName":"Fabian Ruiz Peña","originalName":"Fabian RUIZ PEÑA","nameOnShirt":"FABIÁN","aliases":["Fabian Ruiz Peña","Ruiz Peña Fabian","Fabian Fabián","Fabián","Fabian Ruiz","RUIZ Fabian"],"displayName":"Fabian Ruiz Peña"},"ESP::GAVI":{"teamCode":"ESP","teamName":"Spain","playerName":"GAVI","commonName":"Pablo Paez Gavira","originalName":"Pablo PAEZ GAVIRA","nameOnShirt":"GAVI","aliases":["Pablo Paez Gavira","Paez Gavira Pablo","Pablo Gavi","Gavi"],"zhName":"加維","displayName":"加維（Pablo Paez Gavira）"},"ESP::OLMO Dani":{"teamCode":"ESP","teamName":"Spain","playerName":"OLMO Dani","commonName":"Daniel Olmo Carvajal","originalName":"Daniel OLMO CARVAJAL","nameOnShirt":"OLMO","aliases":["Daniel Olmo Carvajal","Olmo Carvajal Daniel","Daniel Olmo","Olmo","Dani Olmo","OLMO Dani"],"zhName":"达尼·奥尔莫","displayName":"达尼·奥尔莫（Daniel Olmo Carvajal）"},"ESP::PINO Yeremy":{"teamCode":"ESP","teamName":"Spain","playerName":"PINO Yeremy","commonName":"Yeremy Pino Santos","originalName":"Yeremy Jesús PINO SANTOS","nameOnShirt":"YEREMY","aliases":["Yeremy Pino Santos","Yeremy Jesús PINO SANTOS","Pino Santos Yeremy-jesús","Yeremy Yeremy","Yeremy","Yeremy Pino","PINO Yeremy"],"displayName":"Yeremy Pino Santos"},"ESP::PORRO Pedro":{"teamCode":"ESP","teamName":"Spain","playerName":"PORRO Pedro","commonName":"Pedro Porro Sauceda","originalName":"Pedro Antonio PORRO SAUCEDA","nameOnShirt":"PEDRO PORRO","aliases":["Pedro Porro Sauceda","Pedro Antonio PORRO SAUCEDA","Porro Sauceda Pedro-antonio","Pedro Pedro Porro","Pedro Porro","PORRO Pedro"],"zhName":"佩德羅·波洛","displayName":"佩德羅·波洛（Pedro Porro Sauceda）"},"ESP::GARCIA Joan":{"teamCode":"ESP","teamName":"Spain","playerName":"GARCIA Joan","commonName":"Joan Garcia Pons","originalName":"Joan GARCIA PONS","nameOnShirt":"JOAN GARCIA","aliases":["Joan Garcia Pons","Garcia Pons Joan","Joan Joan Garcia","Joan Garcia","GARCIA Joan"],"zhName":"约安·加西亚","displayName":"约安·加西亚（Joan Garcia Pons）"},"ESP::LAPORTE Aymeric":{"teamCode":"ESP","teamName":"Spain","playerName":"LAPORTE Aymeric","commonName":"Aymeric Laporte Fevre","originalName":"Aymeric LAPORTE FEVRE","nameOnShirt":"LAPORTE","aliases":["Aymeric Laporte Fevre","Laporte Fevre Aymeric","Aymeric Laporte","Laporte","LAPORTE Aymeric"],"zhName":"埃梅里克·拉波爾特","displayName":"埃梅里克·拉波爾特（Aymeric Laporte Fevre）"},"ESP::BAENA Alex":{"teamCode":"ESP","teamName":"Spain","playerName":"BAENA Alex","commonName":"Alejandro Baena Rodríguez","originalName":"Alejandro BAENA RODRÍGUEZ","nameOnShirt":"ALEX B.","aliases":["Alejandro Baena Rodríguez","Baena Rodríguez Alejandro","Alejandro Alex B","Alex B","Alex Baena","BAENA Alex"],"displayName":"Alejandro Baena Rodríguez"},"ESP::RODRI":{"teamCode":"ESP","teamName":"Spain","playerName":"RODRI","commonName":"Rodrigo Hernández Cascante","originalName":"Rodrigo HERNÁNDEZ CASCANTE","nameOnShirt":"RODRIGO","aliases":["Rodrigo Hernández Cascante","Hernández Cascante Rodrigo","Rodrigo Rodrigo","Rodrigo","RODRI"],"displayName":"Rodrigo Hernández Cascante"},"ESP::WILLIAMS Nico":{"teamCode":"ESP","teamName":"Spain","playerName":"WILLIAMS Nico","commonName":"Nicholas Williams Arthuer","originalName":"Nicholas WILLIAMS ARTHUER","nameOnShirt":"WILLIAMS JR.","aliases":["Nicholas Williams Arthuer","Williams Arthuer Nicholas","Nicholas Williams Jr","Williams Jr","Nico Williams","WILLIAMS Nico"],"zhName":"尼科·威廉斯","displayName":"尼科·威廉斯（Nicholas Williams Arthuer）"},"ESP::ZUBIMENDI Martin":{"teamCode":"ESP","teamName":"Spain","playerName":"ZUBIMENDI Martin","commonName":"Martin Zubimendi Ibañez","originalName":"Martin ZUBIMENDI IBAÑEZ","nameOnShirt":"ZUBIMENDI","aliases":["Martin Zubimendi Ibañez","Zubimendi Ibañez Martin","Martin Zubimendi","Zubimendi","ZUBIMENDI Martin"],"displayName":"Martin Zubimendi Ibañez"},"ESP::YAMAL Lamine":{"teamCode":"ESP","teamName":"Spain","playerName":"YAMAL Lamine","commonName":"Lamine Nasraoui Ebana","originalName":"Lamine Yamal NASRAOUI EBANA","nameOnShirt":"LAMINE YAMAL","aliases":["Lamine Yamal","Lamine Nasraoui Ebana","Lamine Yamal NASRAOUI EBANA","Nasraoui Ebana Lamine-yamal","Lamine Lamine Yamal","YAMAL Lamine"],"zhName":"拉明·亚马尔","displayName":"拉明·亚马尔（Lamine Nasraoui Ebana）"},"ESP::PEDRI":{"teamCode":"ESP","teamName":"Spain","playerName":"PEDRI","commonName":"Pedro González López","originalName":"Pedro GONZÁLEZ LÓPEZ","nameOnShirt":"PEDRI","aliases":["Pedro González López","González López Pedro","Pedro Pedri","Pedri"],"displayName":"Pedro González López"},"ESP::OYARZABAL Mikel":{"teamCode":"ESP","teamName":"Spain","playerName":"OYARZABAL Mikel","commonName":"Mikel Oyarzabal Ugarte","originalName":"Mikel OYARZABAL UGARTE","nameOnShirt":"OYARZABAL","aliases":["Mikel Oyarzabal Ugarte","Oyarzabal Ugarte Mikel","Mikel Oyarzabal","Oyarzabal","OYARZABAL Mikel"],"zhName":"米克尔·奥亚萨瓦尔","displayName":"米克尔·奥亚萨瓦尔（Mikel Oyarzabal Ugarte）"},"ESP::CUBARSI Pau":{"teamCode":"ESP","teamName":"Spain","playerName":"CUBARSI Pau","commonName":"Pau Cubarsi I Paredes","originalName":"Pau CUBARSI I PAREDES","nameOnShirt":"CUBARSÍ","aliases":["Pau Cubarsi I Paredes","Cubarsi I Paredes Pau","Pau Cubarsí","Cubarsí","CUBARSI Pau"],"zhName":"保·库瓦尔西","displayName":"保·库瓦尔西（Pau Cubarsi I Paredes）"},"ESP::SIMON Unai":{"teamCode":"ESP","teamName":"Spain","playerName":"SIMON Unai","commonName":"Unai Simón Mendibil","originalName":"Unai SIMÓN MENDIBIL","nameOnShirt":"UNAI SIMÓN","aliases":["Unai Simón Mendibil","Simón Mendibil Unai","Unai Unai Simón","Unai Simón","SIMON Unai"],"zhName":"乌奈·西蒙","displayName":"乌奈·西蒙（Unai Simón Mendibil）"},"ESP::CUCURELLA Marc":{"teamCode":"ESP","teamName":"Spain","playerName":"CUCURELLA Marc","commonName":"Marc Cucurella Saseta","originalName":"Marc CUCURELLA SASETA","nameOnShirt":"CUCURELLA","aliases":["Marc Cucurella Saseta","Cucurella Saseta Marc","Marc Cucurella","Cucurella","CUCURELLA Marc"],"zhName":"马克·库库雷利亚","displayName":"马克·库库雷利亚（Marc Cucurella Saseta）"},"ESP::MUNOZ Victor":{"teamCode":"ESP","teamName":"Spain","playerName":"MUNOZ Victor","commonName":"Victor Muñoz Villanueva","originalName":"Victor MUÑOZ VILLANUEVA","nameOnShirt":"VICTOR M.V.","aliases":["Victor Muñoz Villanueva","Muñoz Villanueva Victor","Victor Victor Mv","Victor Mv","Victor Munoz","MUNOZ Victor"],"displayName":"Victor Muñoz Villanueva"},"ESP::IGLESIAS Borja":{"teamCode":"ESP","teamName":"Spain","playerName":"IGLESIAS Borja","commonName":"Borja Iglesias Quintás","originalName":"Borja IGLESIAS QUINTÁS","nameOnShirt":"B. IGLESIAS","aliases":["Borja Iglesias Quintás","Iglesias Quintás Borja","Borja B Iglesias","B Iglesias","Borja Iglesias","IGLESIAS Borja"],"zhName":"博爾哈·伊格萊西亞斯","displayName":"博爾哈·伊格萊西亞斯（Borja Iglesias Quintás）"}}}
